MANIFEST.in
README
setup.py
chunks/.project
chunks/.pydevproject
chunks/__init__.py
chunks/admin.py
chunks/models.py
chunks/migrations/0001_initial.py
chunks/migrations/0002_auto__add_field_chunk_description.py
chunks/migrations/__init__.py
chunks/redsolution_setup/__init__.py
chunks/redsolution_setup/__init__.pyo
chunks/redsolution_setup/make.py
chunks/redsolution_setup/make.pyo
chunks/redsolution_setup/templates/chunks/redsolutioncms/base_chunks.html
chunks/redsolution_setup/templates/chunks/redsolutioncms/robots.txt
chunks/redsolution_setup/templates/chunks/redsolutioncms/settings.pyt
chunks/redsolution_setup/templates/chunks/redsolutioncms/urls.pyt
chunks/templatetags/__init__.py
chunks/templatetags/chunks.py
redsolutioncms.django_chunks.egg-info/PKG-INFO
redsolutioncms.django_chunks.egg-info/SOURCES.txt
redsolutioncms.django_chunks.egg-info/dependency_links.txt
redsolutioncms.django_chunks.egg-info/entry_points.txt
redsolutioncms.django_chunks.egg-info/not-zip-safe
redsolutioncms.django_chunks.egg-info/top_level.txt