Metadata-Version: 1.1
Name: redsolutioncms.django-chunks
Version: 0.2.2
Summary: Parts of reusable content across your site. Usable for validation meta codes, 
Home-page: http://code.google.com/p/django-chunks/
Author: Clint Ecker
Author-email: me@clintecker.com
License: UNKNOWN
Platform: UNKNOWN
Classifier: Development Status :: 4 - Beta
Classifier: Environment :: Web Environment
Classifier: Intended Audience :: Developers
Classifier: License :: OSI Approved :: BSD License
Classifier: Operating System :: OS Independent
Classifier: Programming Language :: Python
Classifier: Topic :: Utilities
